<?xml version="1.0" encoding="UTF-8"?><wfs:FeatureCollection xmlns:wfs="http://www.opengis.net/wfs/2.0" xmlns:xs="http://www.w3.org/2001/XMLSchema" xmlns:ef="http://inspire.ec.europa.eu/schemas/ef/4.0" xmlns:gco="http://www.isotc211.org/2005/gco" xmlns:base2="http://inspire.ec.europa.eu/schemas/base2/2.0" xmlns:gml="http://www.opengis.net/gml/3.2" xmlns:base="http://inspire.ec.europa.eu/schemas/base/3.3" xmlns:xlink="http://www.w3.org/1999/xlink" xmlns:xsi="http://www.w3.org/2001/XMLSchema-instance" numberMatched="unknown" numberReturned="5" timeStamp="2016-02-29T11:12:44.173Z" xsi:schemaLocation="http://www.opengis.net/wfs/2.0 http://schemas.opengis.net/wfs/2.0/wfs.xsd http://inspire.ec.europa.eu/schemas/ef/4.0 http://inspire.ec.europa.eu/schemas/ef/4.0/EnvironmentalMonitoringFacilities.xsd http://www.opengis.net/gml/3.2 http://schemas.opengis.net/gml/3.2.1/gml.xsd"><wfs:member><ef:EnvironmentalMonitoringFacility gml:id="Piezometre.1.00058X0108-111111"><gml:description>Water well from national BSS (Banque du Sous-Sol) Data database. Piezometer monitoring ground water level</gml:description><gml:identifier codeSpace="http://www.ietf.org/rfc/rfc2616">http://ressource.brgm.fr/data/Piezometre/1.00058X0108/111111</gml:identifier><ef:inspireId><base:Identifier><base:localId>1.00058X0108/111111</base:localId><base:namespace>http://ressource.brgm.fr/data/Piezometre/</base:namespace><base:versionId/></base:Identifier></ef:inspireId><ef:additionalDescription/><ef:mediaMonitored xlink:href="http://inspire.ec.europa.eu/codelist/MediaValue/water" xlink:title="water"/><ef:legalBackground/><ef:geometry><gml:Point gml:id="Piezometre.geom.1.00058X0108-111111" srsDimension="2" srsName="urn:ogc:def:crs:EPSG::4326"><gml:pos>50.796816076535 1.77303517272897</gml:pos></gml:Point></ef:geometry><ef:onlineResource>http://fichebsseau.brgm.fr/bss_eau/fiche.jsf?code=00058X0108/111111</ef:onlineResource><ef:purpose xlink:href="http://www.sandre.eaufrance.fr/?urn=urn:sandre:donnees:148::CdElement:2:::referentiel:3.1:xml" xlink:title="Mesure quantité (piézométrie)"/><ef:broader/><ef:supersedes/><ef:supersededBy/><ef:reportedTo xsi:nil="true" nilReason="unpopulated"/><ef:hasObservation xlink:href="http://ressource.brgm.fr/obs/ChroniquePiezometrique/xxx" xlink:title="ChroniquePiezométrique xxx"/><ef:involvedIn/><ef:representativePoint><gml:Point gml:id="Piezometre.reppoint.1.00058X0108-111111" srsDimension="2" srsName="urn:ogc:def:crs:EPSG::4326"><gml:pos>50.796816076535 1.77303517272897</gml:pos></gml:Point></ef:representativePoint><ef:measurementRegime/><ef:mobile>false</ef:mobile><ef:resultAcquisitionSource xlink:href="http://inspire.ec.europa.eu/codelist/ResultAcquisitionSourceValue/inSitu/" xlink:title="in-situ"/><ef:specialisedEMFType xlink:href="http://www.sandre.eaufrance.fr/urn.php?urn=urn:sandre:dictionnaire:PTE::entite:Piezometre:ressource:2.1:::html" xlink:title="Piezometre"/><ef:operationalActivityPeriod><ef:OperationalActivityPeriod gml:id="Piezometre.OperationalActivityPeriod.1.00058X0108-111111"><ef:activityTime><gml:TimePeriod gml:id="TimePeriod.2.314816"><gml:beginPosition/><gml:endPosition/></gml:TimePeriod></ef:activityTime></ef:OperationalActivityPeriod></ef:operationalActivityPeriod><ef:relatedTo/></ef:EnvironmentalMonitoringFacility></wfs:member><wfs:member><ef:EnvironmentalMonitoringFacility gml:id="Piezometre.1.01143X0062-F"><gml:description>Water well from national BSS (Banque du Sous-Sol) Data database. Piezometer monitoring ground water level</gml:description><gml:identifier codeSpace="http://www.ietf.org/rfc/rfc2616">http://ressource.brgm.fr/data/Piezometre/1.01143X0062/F</gml:identifier><ef:inspireId><base:Identifier><base:localId>1.01143X0062/F</base:localId><base:namespace>http://ressource.brgm.fr/data/Piezometre/</base:namespace><base:versionId/></base:Identifier></ef:inspireId><ef:additionalDescription/><ef:mediaMonitored xlink:href="http://inspire.ec.europa.eu/codelist/MediaValue/water" xlink:title="water"/><ef:legalBackground/><ef:geometry><gml:Point gml:id="Piezometre.geom.1.01143X0062-F" srsDimension="2" srsName="urn:ogc:def:crs:EPSG::4326"><gml:pos>49.4492372911424 6.34787602004069</gml:pos></gml:Point></ef:geometry><ef:onlineResource>http://fichebsseau.brgm.fr/bss_eau/fiche.jsf?code=01143X0062/F</ef:onlineResource><ef:purpose xlink:href="http://www.sandre.eaufrance.fr/?urn=urn:sandre:donnees:148::CdElement:2:::referentiel:3.1:xml" xlink:title="Mesure quantité (piézométrie)"/><ef:observingCapability><ef:ObservingCapability gml:id="ef_observingcapability.fid-3a57c72a_1532cb9bf84_2cb7"><ef:observingTime><gml:TimePeriod gml:id="ObservingCapability.TimePeriod.8541"><gml:beginPosition>2010-07-14T22:00:00Z</gml:beginPosition><gml:endPosition>2010-07-14T22:00:00Z</gml:endPosition></gml:TimePeriod></ef:observingTime><ef:processType xlink:href="http://inspire.ec.europa.eu/codelist/ProcessTypeValue/process/" xlink:title="Process"/><ef:resultNature xlink:href="http://inspire.ec.europa.eu/codelist/ResultNatureValue/primary/" xlink:title="primary"/><ef:procedure/><ef:featureOfInterest xlink:href="http://ressource.brgm.fr/data/EntiteHydroGeol/143AK05" xlink:title=""/><ef:observedProperty xlink:href="http://ressource.brgm.fr/data/somePath" xlink:title="GroundWaterLevel"/></ef:ObservingCapability></ef:observingCapability><ef:observingCapability><ef:ObservingCapability gml:id="ef_observingcapability.fid-3a57c72a_1532cb9bf84_2cba"><ef:observingTime><gml:TimePeriod gml:id="ObservingCapability.TimePeriod.8542"><gml:beginPosition>2010-07-14T22:00:00Z</gml:beginPosition><gml:endPosition>2010-07-14T22:00:00Z</gml:endPosition></gml:TimePeriod></ef:observingTime><ef:processType xlink:href="http://inspire.ec.europa.eu/codelist/ProcessTypeValue/process/" xlink:title="Process"/><ef:resultNature xlink:href="http://inspire.ec.europa.eu/codelist/ResultNatureValue/primary/" xlink:title="primary"/><ef:procedure/><ef:featureOfInterest xlink:href="http://ressource.brgm.fr/data/EntiteHydroGeol/143AK03" xlink:title=""/><ef:observedProperty xlink:href="http://ressource.brgm.fr/data/somePath" xlink:title="GroundWaterLevel"/></ef:ObservingCapability></ef:observingCapability><ef:observingCapability><ef:ObservingCapability gml:id="ef_observingcapability.fid-3a57c72a_1532cb9bf84_2cbb"><ef:observingTime><gml:TimePeriod gml:id="ObservingCapability.TimePeriod.8543"><gml:beginPosition>2010-07-14T22:00:00Z</gml:beginPosition><gml:endPosition>2010-07-14T22:00:00Z</gml:endPosition></gml:TimePeriod></ef:observingTime><ef:processType xlink:href="http://inspire.ec.europa.eu/codelist/ProcessTypeValue/process/" xlink:title="Process"/><ef:resultNature xlink:href="http://inspire.ec.europa.eu/codelist/ResultNatureValue/primary/" xlink:title="primary"/><ef:procedure/><ef:featureOfInterest xlink:href="http://ressource.brgm.fr/data/EntiteHydroGeol/143AK01" xlink:title=""/><ef:observedProperty xlink:href="http://ressource.brgm.fr/data/somePath" xlink:title="GroundWaterLevel"/></ef:ObservingCapability></ef:observingCapability><ef:broader/><ef:supersedes/><ef:supersededBy/><ef:reportedTo xsi:nil="true" nilReason="unpopulated"/><ef:hasObservation xlink:href="http://ressource.brgm.fr/obs/ChroniquePiezometrique/xxx" xlink:title="ChroniquePiezométrique xxx"/><ef:involvedIn/><ef:representativePoint><gml:Point gml:id="Piezometre.reppoint.1.01143X0062-F" srsDimension="2" srsName="urn:ogc:def:crs:EPSG::4326"><gml:pos>49.4492372911424 6.34787602004069</gml:pos></gml:Point></ef:representativePoint><ef:measurementRegime xlink:href="http://inspire.ec.europa.eu/codelist/MeasurementRegimeValue/demandDrivenDataCollection/" xlink:title="demandDrivenDataCollection"/><ef:mobile>false</ef:mobile><ef:resultAcquisitionSource xlink:href="http://inspire.ec.europa.eu/codelist/ResultAcquisitionSourceValue/inSitu/" xlink:title="in-situ"/><ef:specialisedEMFType xlink:href="http://www.sandre.eaufrance.fr/urn.php?urn=urn:sandre:dictionnaire:PTE::entite:Piezometre:ressource:2.1:::html" xlink:title="Piezometre"/><ef:operationalActivityPeriod><ef:OperationalActivityPeriod gml:id="Piezometre.OperationalActivityPeriod.1.01143X0062-F"><ef:activityTime><gml:TimePeriod gml:id="TimePeriod.2.204910"><gml:beginPosition>2010-07-14T22:00:00Z</gml:beginPosition><gml:endPosition>2010-07-14T22:00:00Z</gml:endPosition></gml:TimePeriod></ef:activityTime></ef:OperationalActivityPeriod></ef:operationalActivityPeriod><ef:relatedTo/><ef:belongsTo><ef:NetworkFacility gml:id="ef_networkfacility.fid-3a57c72a_1532cb9bf84_2cb8"><ef:linkingTime><gml:TimePeriod gml:id="TimePeriod.0200000041.01143X0062-F"><gml:beginPosition>1899-12-31T23:00:00Z</gml:beginPosition><gml:endPosition/></gml:TimePeriod></ef:linkingTime><ef:belongsTo xlink:href="http://ressource.brgm.fr/data/DispositifCollecte/0200000041" xlink:title="Réseau de suivi piézométrique de la nappe des Grès du Trias inférieur sous couverture(RRESOUPGTI)"/><ef:contains/></ef:NetworkFacility></ef:belongsTo></ef:EnvironmentalMonitoringFacility></wfs:member><wfs:member><ef:EnvironmentalMonitoringFacility gml:id="Piezometre.1.01151X0021-F3"><gml:description>Water well from national BSS (Banque du Sous-Sol) Data database. Piezometer monitoring ground water level</gml:description><gml:identifier codeSpace="http://www.ietf.org/rfc/rfc2616">http://ressource.brgm.fr/data/Piezometre/1.01151X0021/F3</gml:identifier><ef:inspireId><base:Identifier><base:localId>1.01151X0021/F3</base:localId><base:namespace>http://ressource.brgm.fr/data/Piezometre/</base:namespace><base:versionId/></base:Identifier></ef:inspireId><ef:name>Grès du Trias inférieur (GTI) à LAUNSTROFF  </ef:name><ef:additionalDescription/><ef:mediaMonitored xlink:href="http://inspire.ec.europa.eu/codelist/MediaValue/water" xlink:title="water"/><ef:legalBackground/><ef:geometry><gml:Point gml:id="Piezometre.geom.1.01151X0021-F3" srsDimension="2" srsName="urn:ogc:def:crs:EPSG::4326"><gml:pos>49.4258323637302 6.50136709047319</gml:pos></gml:Point></ef:geometry><ef:onlineResource>http://fichebsseau.brgm.fr/bss_eau/fiche.jsf?code=01151X0021/F3</ef:onlineResource><ef:purpose xlink:href="http://www.sandre.eaufrance.fr/?urn=urn:sandre:donnees:148::CdElement:2:::referentiel:3.1:xml" xlink:title="Mesure quantité (piézométrie)"/><ef:observingCapability><ef:ObservingCapability gml:id="ef_observingcapability.fid-3a57c72a_1532cb9bf84_2cbc"><ef:observingTime><gml:TimePeriod gml:id="ObservingCapability.TimePeriod.8115"><gml:beginPosition>2010-09-01T22:00:00Z</gml:beginPosition><gml:endPosition>2010-09-01T22:00:00Z</gml:endPosition></gml:TimePeriod></ef:observingTime><ef:processType xlink:href="http://inspire.ec.europa.eu/codelist/ProcessTypeValue/process/" xlink:title="Process"/><ef:resultNature xlink:href="http://inspire.ec.europa.eu/codelist/ResultNatureValue/primary/" xlink:title="primary"/><ef:procedure/><ef:featureOfInterest xlink:href="http://ressource.brgm.fr/data/EntiteHydroGeol/143AK05" xlink:title=""/><ef:observedProperty xlink:href="http://ressource.brgm.fr/data/somePath" xlink:title="GroundWaterLevel"/></ef:ObservingCapability></ef:observingCapability><ef:broader/><ef:supersedes/><ef:supersededBy/><ef:reportedTo xsi:nil="true" nilReason="unpopulated"/><ef:hasObservation xlink:href="http://ressource.brgm.fr/obs/ChroniquePiezometrique/xxx" xlink:title="ChroniquePiezométrique xxx"/><ef:involvedIn/><ef:representativePoint><gml:Point gml:id="Piezometre.reppoint.1.01151X0021-F3" srsDimension="2" srsName="urn:ogc:def:crs:EPSG::4326"><gml:pos>49.4258323637302 6.50136709047319</gml:pos></gml:Point></ef:representativePoint><ef:measurementRegime xlink:href="http://inspire.ec.europa.eu/codelist/MeasurementRegimeValue/demandDrivenDataCollection/" xlink:title="demandDrivenDataCollection"/><ef:mobile>false</ef:mobile><ef:resultAcquisitionSource xlink:href="http://inspire.ec.europa.eu/codelist/ResultAcquisitionSourceValue/inSitu/" xlink:title="in-situ"/><ef:specialisedEMFType xlink:href="http://www.sandre.eaufrance.fr/urn.php?urn=urn:sandre:dictionnaire:PTE::entite:Piezometre:ressource:2.1:::html" xlink:title="Piezometre"/><ef:operationalActivityPeriod><ef:OperationalActivityPeriod gml:id="Piezometre.OperationalActivityPeriod.1.01151X0021-F3"><ef:activityTime><gml:TimePeriod gml:id="TimePeriod.2.203617"><gml:beginPosition>2010-09-01T22:00:00Z</gml:beginPosition><gml:endPosition>2010-09-01T22:00:00Z</gml:endPosition></gml:TimePeriod></ef:activityTime></ef:OperationalActivityPeriod></ef:operationalActivityPeriod><ef:relatedTo/><ef:belongsTo><ef:NetworkFacility gml:id="ef_networkfacility.fid-3a57c72a_1532cb9bf84_2cbd"><ef:linkingTime><gml:TimePeriod gml:id="TimePeriod.0000000028.01151X0021-F3"><gml:beginPosition>1899-12-31T23:00:00Z</gml:beginPosition><gml:endPosition/></gml:TimePeriod></ef:linkingTime><ef:belongsTo xlink:href="http://ressource.brgm.fr/data/DispositifCollecte/0000000028" xlink:title="Réseau national de suivi au titre du contrôle sanitaire sur les eaux brutes utilisées pour la production d'eau potable(RNSISEAU)"/><ef:contains/></ef:NetworkFacility></ef:belongsTo><ef:belongsTo><ef:NetworkFacility gml:id="ef_networkfacility.fid-3a57c72a_1532cb9bf84_2cc0"><ef:linkingTime><gml:TimePeriod gml:id="TimePeriod.0200000014.01151X0021-F3"><gml:beginPosition>2003-07-31T22:00:00Z</gml:beginPosition><gml:endPosition/></gml:TimePeriod></ef:linkingTime><ef:belongsTo xlink:href="http://ressource.brgm.fr/data/DispositifCollecte/0200000014" xlink:title="Inventaire de la qualité des eaux souterraines de la région Lorraine(RRINVLOR)"/><ef:contains/></ef:NetworkFacility></ef:belongsTo><ef:belongsTo><ef:NetworkFacility gml:id="ef_networkfacility.fid-3a57c72a_1532cb9bf84_2cc1"><ef:linkingTime><gml:TimePeriod gml:id="TimePeriod.0200000041.01151X0021-F3"><gml:beginPosition>1899-12-31T23:00:00Z</gml:beginPosition><gml:endPosition/></gml:TimePeriod></ef:linkingTime><ef:belongsTo xlink:href="http://ressource.brgm.fr/data/DispositifCollecte/0200000041" xlink:title="Réseau de suivi piézométrique de la nappe des Grès du Trias inférieur sous couverture(RRESOUPGTI)"/><ef:contains/></ef:NetworkFacility></ef:belongsTo></ef:EnvironmentalMonitoringFacility></wfs:member><wfs:member><ef:EnvironmentalMonitoringFacility gml:id="Piezometre.1.01368X0008-KG"><gml:description>Water well from national BSS (Banque du Sous-Sol) Data database. Piezometer monitoring ground water level</gml:description><gml:identifier codeSpace="http://www.ietf.org/rfc/rfc2616">http://ressource.brgm.fr/data/Piezometre/1.01368X0008/KG</gml:identifier><ef:inspireId><base:Identifier><base:localId>1.01368X0008/KG</base:localId><base:namespace>http://ressource.brgm.fr/data/Piezometre/</base:namespace><base:versionId/></base:Identifier></ef:inspireId><ef:name>Calcaires du Dogger sous couverture à SAINT-JEAN -LES-BUZY</ef:name><ef:additionalDescription/><ef:mediaMonitored xlink:href="http://inspire.ec.europa.eu/codelist/MediaValue/water" xlink:title="water"/><ef:legalBackground/><ef:responsibleParty><base2:RelatedParty><base2:organisationName><gco:CharacterString>EAULOR_S</gco:CharacterString></base2:organisationName></base2:RelatedParty></ef:responsibleParty><ef:geometry><gml:Point gml:id="Piezometre.geom.1.01368X0008-KG" srsDimension="2" srsName="urn:ogc:def:crs:EPSG::4326"><gml:pos>49.1633302224248 5.72742778861341</gml:pos></gml:Point></ef:geometry><ef:onlineResource>http://fichebsseau.brgm.fr/bss_eau/fiche.jsf?code=01368X0008/KG</ef:onlineResource><ef:purpose xlink:href="http://www.sandre.eaufrance.fr/?urn=urn:sandre:donnees:148::CdElement:2:::referentiel:3.1:xml" xlink:title="Mesure quantité (piézométrie)"/><ef:broader/><ef:supersedes/><ef:supersededBy/><ef:reportedTo xsi:nil="true" nilReason="unpopulated"/><ef:hasObservation xlink:href="http://ressource.brgm.fr/obs/ChroniquePiezometrique/xxx" xlink:title="ChroniquePiezométrique xxx"/><ef:involvedIn/><ef:representativePoint><gml:Point gml:id="Piezometre.reppoint.1.01368X0008-KG" srsDimension="2" srsName="urn:ogc:def:crs:EPSG::4326"><gml:pos>49.1633302224248 5.72742778861341</gml:pos></gml:Point></ef:representativePoint><ef:measurementRegime/><ef:mobile>false</ef:mobile><ef:resultAcquisitionSource xlink:href="http://inspire.ec.europa.eu/codelist/ResultAcquisitionSourceValue/inSitu/" xlink:title="in-situ"/><ef:specialisedEMFType xlink:href="http://www.sandre.eaufrance.fr/urn.php?urn=urn:sandre:dictionnaire:PTE::entite:Piezometre:ressource:2.1:::html" xlink:title="Piezometre"/><ef:operationalActivityPeriod><ef:OperationalActivityPeriod gml:id="Piezometre.OperationalActivityPeriod.1.01368X0008-KG"><ef:activityTime><gml:TimePeriod gml:id="TimePeriod.2.248130"><gml:beginPosition>2009-05-02T05:00:00Z</gml:beginPosition><gml:endPosition>2010-01-17T07:00:00Z</gml:endPosition></gml:TimePeriod></ef:activityTime></ef:OperationalActivityPeriod></ef:operationalActivityPeriod><ef:relatedTo/><ef:belongsTo><ef:NetworkFacility gml:id="ef_networkfacility.fid-3a57c72a_1532cb9bf84_2cc2"><ef:linkingTime><gml:TimePeriod gml:id="TimePeriod.RH-MEUS-TP.01368X0008-KG"><gml:beginPosition>2000-05-30T10:36:47Z</gml:beginPosition><gml:endPosition/></gml:TimePeriod></ef:linkingTime><ef:belongsTo xlink:href="http://ressource.brgm.fr/data/DispositifCollecte/RH-MEUS-TP" xlink:title="RESEAU QUALITE DES EAUX SOUTERRAINES  EN RHIN MEUSE"/><ef:contains/></ef:NetworkFacility></ef:belongsTo><ef:belongsTo><ef:NetworkFacility gml:id="ef_networkfacility.fid-3a57c72a_1532cb9bf84_2cc5"><ef:linkingTime><gml:TimePeriod gml:id="TimePeriod.0000000029.01368X0008-KG"><gml:beginPosition>2008-08-05T22:00:00Z</gml:beginPosition><gml:endPosition>2010-01-31T23:00:00Z</gml:endPosition></gml:TimePeriod></ef:linkingTime><ef:belongsTo xlink:href="http://ressource.brgm.fr/data/DispositifCollecte/0000000029" xlink:title="Réseau patrimonial national de suivi quantitatif des eaux souterraines(RNESP)"/><ef:contains/></ef:NetworkFacility></ef:belongsTo><ef:belongsTo><ef:NetworkFacility gml:id="ef_networkfacility.fid-3a57c72a_1532cb9bf84_2cc6"><ef:linkingTime><gml:TimePeriod gml:id="TimePeriod.0200000002.01368X0008-KG"><gml:beginPosition>2008-08-05T22:00:00Z</gml:beginPosition><gml:endPosition>2010-01-31T23:00:00Z</gml:endPosition></gml:TimePeriod></ef:linkingTime><ef:belongsTo xlink:href="http://ressource.brgm.fr/data/DispositifCollecte/0200000002" xlink:title="Méta Réseau de suivi piézométrique des eaux souterraines du bassin Rhin-Meuse (RBEST)(RBESOUPRM)"/><ef:contains/></ef:NetworkFacility></ef:belongsTo><ef:belongsTo><ef:NetworkFacility gml:id="ef_networkfacility.fid-3a57c72a_1532cb9bf84_2cc7"><ef:linkingTime><gml:TimePeriod gml:id="TimePeriod.0200000013.01368X0008-KG"><gml:beginPosition>2002-03-27T23:00:00Z</gml:beginPosition><gml:endPosition>2010-12-30T23:00:00Z</gml:endPosition></gml:TimePeriod></ef:linkingTime><ef:belongsTo xlink:href="http://ressource.brgm.fr/data/DispositifCollecte/0200000013" xlink:title="Réseau de suivi de la qualité des eaux souterraines du Bassin Ferrifère Lorrain(RRESOUQBFL)"/><ef:contains/></ef:NetworkFacility></ef:belongsTo><ef:belongsTo><ef:NetworkFacility gml:id="ef_networkfacility.fid-3a57c72a_1532cb9bf84_2cc8"><ef:linkingTime><gml:TimePeriod gml:id="TimePeriod.0200000014.01368X0008-KG"><gml:beginPosition>2003-07-31T22:00:00Z</gml:beginPosition><gml:endPosition/></gml:TimePeriod></ef:linkingTime><ef:belongsTo xlink:href="http://ressource.brgm.fr/data/DispositifCollecte/0200000014" xlink:title="Inventaire de la qualité des eaux souterraines de la région Lorraine(RRINVLOR)"/><ef:contains/></ef:NetworkFacility></ef:belongsTo><ef:belongsTo><ef:NetworkFacility gml:id="ef_networkfacility.fid-3a57c72a_1532cb9bf84_2cc9"><ef:linkingTime><gml:TimePeriod gml:id="TimePeriod.0200000078.01368X0008-KG"><gml:beginPosition>2008-08-05T22:00:00Z</gml:beginPosition><gml:endPosition>2010-01-31T23:00:00Z</gml:endPosition></gml:TimePeriod></ef:linkingTime><ef:belongsTo xlink:href="http://ressource.brgm.fr/data/DispositifCollecte/0200000078" xlink:title="Réseau de suivi piézométrique des eaux souterraines du BRGM Lorraine(RRESOUPBRGMLOR)"/><ef:contains/></ef:NetworkFacility></ef:belongsTo><ef:belongsTo><ef:NetworkFacility gml:id="ef_networkfacility.fid-3a57c72a_1532cb9bf84_2cca"><ef:linkingTime><gml:TimePeriod gml:id="TimePeriod.0000000073.01368X0008-KG"><gml:beginPosition>2008-08-05T22:00:00Z</gml:beginPosition><gml:endPosition>2010-01-31T23:00:00Z</gml:endPosition></gml:TimePeriod></ef:linkingTime><ef:belongsTo xlink:href="http://ressource.brgm.fr/data/DispositifCollecte/0000000073" xlink:title="Réseau national de suivi quantitatif des eaux souterraines sous MO BRGM(RNESOUPMOBRGM)"/><ef:contains/></ef:NetworkFacility></ef:belongsTo><ef:belongsTo><ef:NetworkFacility gml:id="ef_networkfacility.fid-3a57c72a_1532cb9bf84_2ccb"><ef:linkingTime><gml:TimePeriod gml:id="TimePeriod.0000000070.01368X0008-KG"><gml:beginPosition>2008-08-05T22:00:00Z</gml:beginPosition><gml:endPosition>2010-01-31T23:00:00Z</gml:endPosition></gml:TimePeriod></ef:linkingTime><ef:belongsTo xlink:href="http://ressource.brgm.fr/data/DispositifCollecte/0000000070" xlink:title="Surveillance de l'état quantitatif des eaux souterraines de la France(FR_SOP)"/><ef:contains/></ef:NetworkFacility></ef:belongsTo><ef:belongsTo><ef:NetworkFacility gml:id="ef_networkfacility.fid-3a57c72a_1532cb9bf84_2ccc"><ef:linkingTime><gml:TimePeriod gml:id="TimePeriod.0200000066.01368X0008-KG"><gml:beginPosition>2008-08-05T22:00:00Z</gml:beginPosition><gml:endPosition>2010-01-31T23:00:00Z</gml:endPosition></gml:TimePeriod></ef:linkingTime><ef:belongsTo xlink:href="http://ressource.brgm.fr/data/DispositifCollecte/0200000066" xlink:title="Surveillance de l'état quantitatif des eaux souterraines du bassin Rhin(FRCSOP)"/><ef:contains/></ef:NetworkFacility></ef:belongsTo><ef:belongsTo><ef:NetworkFacility gml:id="ef_networkfacility.fid-3a57c72a_1532cb9bf84_2ccd"><ef:linkingTime><gml:TimePeriod gml:id="TimePeriod.0200000101.01368X0008-KG"><gml:beginPosition>2002-03-27T23:00:00Z</gml:beginPosition><gml:endPosition>2010-12-30T23:00:00Z</gml:endPosition></gml:TimePeriod></ef:linkingTime><ef:belongsTo xlink:href="http://ressource.brgm.fr/data/DispositifCollecte/0200000101" xlink:title="Méta-réseau de suivi de la qualité des eaux souterraines sur le territoire du SAGE(RRESOUQSAGELOR)"/><ef:contains/></ef:NetworkFacility></ef:belongsTo><ef:belongsTo><ef:NetworkFacility gml:id="ef_networkfacility.fid-3a57c72a_1532cb9bf84_2cce"><ef:linkingTime><gml:TimePeriod gml:id="TimePeriod.0200000004.01368X0008-KG"><gml:beginPosition>1899-12-31T23:00:00Z</gml:beginPosition><gml:endPosition/></gml:TimePeriod></ef:linkingTime><ef:belongsTo xlink:href="http://ressource.brgm.fr/data/DispositifCollecte/0200000004" xlink:title="Réseau de suivi piézométrique des eaux souterraines du bassin Rhin-Meuse (MO BRGM)(RBESOUPRMBRGM)"/><ef:contains/></ef:NetworkFacility></ef:belongsTo></ef:EnvironmentalMonitoringFacility></wfs:member><wfs:member><ef:EnvironmentalMonitoringFacility gml:id="Piezometre.1.01381X0069-S"><gml:description>Water well from national BSS (Banque du Sous-Sol) Data database. Piezometer monitoring ground water level</gml:description><gml:identifier codeSpace="http://www.ietf.org/rfc/rfc2616">http://ressource.brgm.fr/data/Piezometre/1.01381X0069/S</gml:identifier><ef:inspireId><base:Identifier><base:localId>1.01381X0069/S</base:localId><base:namespace>http://ressource.brgm.fr/data/Piezometre/</base:namespace><base:versionId/></base:Identifier></ef:inspireId><ef:name>Alluvions de la Moselle à RICHEMONT</ef:name><ef:additionalDescription/><ef:mediaMonitored xlink:href="http://inspire.ec.europa.eu/codelist/MediaValue/water" xlink:title="water"/><ef:legalBackground/><ef:responsibleParty><base2:RelatedParty><base2:organisationName><gco:CharacterString>EAULOR_S</gco:CharacterString></base2:organisationName></base2:RelatedParty></ef:responsibleParty><ef:geometry><gml:Point gml:id="Piezometre.geom.1.01381X0069-S" srsDimension="2" srsName="urn:ogc:def:crs:EPSG::4326"><gml:pos>49.2899870403701 6.16107439916643</gml:pos></gml:Point></ef:geometry><ef:onlineResource>http://fichebsseau.brgm.fr/bss_eau/fiche.jsf?code=01381X0069/S</ef:onlineResource><ef:purpose xlink:href="http://www.sandre.eaufrance.fr/?urn=urn:sandre:donnees:148::CdElement:2:::referentiel:3.1:xml" xlink:title="Mesure quantité (piézométrie)"/><ef:observingCapability><ef:ObservingCapability gml:id="ef_observingcapability.fid-3a57c72a_1532cb9bf84_2cbf"><ef:observingTime><gml:TimePeriod gml:id="ObservingCapability.TimePeriod.10955"><gml:beginPosition>1970-01-04T23:00:00Z</gml:beginPosition><gml:endPosition>2014-09-22T23:00:00Z</gml:endPosition></gml:TimePeriod></ef:observingTime><ef:processType xlink:href="http://inspire.ec.europa.eu/codelist/ProcessTypeValue/process/" xlink:title="Process"/><ef:resultNature xlink:href="http://inspire.ec.europa.eu/codelist/ResultNatureValue/primary/" xlink:title="primary"/><ef:procedure/><ef:featureOfInterest xlink:href="http://ressource.brgm.fr/data/EntiteHydroGeol/040AC21" xlink:title=""/><ef:observedProperty xlink:href="http://ressource.brgm.fr/data/somePath" xlink:title="GroundWaterLevel"/></ef:ObservingCapability></ef:observingCapability><ef:broader/><ef:supersedes/><ef:supersededBy/><ef:reportedTo xsi:nil="true" nilReason="unpopulated"/><ef:hasObservation xlink:href="http://ressource.brgm.fr/obs/ChroniquePiezometrique/xxx" xlink:title="ChroniquePiezométrique xxx"/><ef:involvedIn/><ef:representativePoint><gml:Point gml:id="Piezometre.reppoint.1.01381X0069-S" srsDimension="2" srsName="urn:ogc:def:crs:EPSG::4326"><gml:pos>49.2899870403701 6.16107439916643</gml:pos></gml:Point></ef:representativePoint><ef:measurementRegime xlink:href="http://inspire.ec.europa.eu/codelist/MeasurementRegimeValue/demandDrivenDataCollection/" xlink:title="demandDrivenDataCollection"/><ef:mobile>false</ef:mobile><ef:resultAcquisitionSource xlink:href="http://inspire.ec.europa.eu/codelist/ResultAcquisitionSourceValue/inSitu/" xlink:title="in-situ"/><ef:specialisedEMFType xlink:href="http://www.sandre.eaufrance.fr/urn.php?urn=urn:sandre:dictionnaire:PTE::entite:Piezometre:ressource:2.1:::html" xlink:title="Piezometre"/><ef:operationalActivityPeriod><ef:OperationalActivityPeriod gml:id="Piezometre.OperationalActivityPeriod.1.01381X0069-S"><ef:activityTime><gml:TimePeriod gml:id="TimePeriod.2.285584"><gml:beginPosition>1970-01-04T23:00:00Z</gml:beginPosition><gml:endPosition>2014-09-22T23:00:00Z</gml:endPosition></gml:TimePeriod></ef:activityTime></ef:OperationalActivityPeriod></ef:operationalActivityPeriod><ef:relatedTo/><ef:belongsTo><ef:NetworkFacility gml:id="ef_networkfacility.fid-3a57c72a_1532cb9bf84_2ccf"><ef:linkingTime><gml:TimePeriod gml:id="TimePeriod.0200000066.01381X0069-S"><gml:beginPosition>1970-01-04T23:00:00Z</gml:beginPosition><gml:endPosition/></gml:TimePeriod></ef:linkingTime><ef:belongsTo xlink:href="http://ressource.brgm.fr/data/DispositifCollecte/0200000066" xlink:title="Surveillance de l'état quantitatif des eaux souterraines du bassin Rhin(FRCSOP)"/><ef:contains/></ef:NetworkFacility></ef:belongsTo><ef:belongsTo><ef:NetworkFacility gml:id="ef_networkfacility.fid-3a57c72a_1532cb9bf84_2cd0"><ef:linkingTime><gml:TimePeriod gml:id="TimePeriod.0000000070.01381X0069-S"><gml:beginPosition>1970-01-04T23:00:00Z</gml:beginPosition><gml:endPosition/></gml:TimePeriod></ef:linkingTime><ef:belongsTo xlink:href="http://ressource.brgm.fr/data/DispositifCollecte/0000000070" xlink:title="Surveillance de l'état quantitatif des eaux souterraines de la France(FR_SOP)"/><ef:contains/></ef:NetworkFacility></ef:belongsTo><ef:belongsTo><ef:NetworkFacility gml:id="ef_networkfacility.fid-3a57c72a_1532cb9bf84_2cd1"><ef:linkingTime><gml:TimePeriod gml:id="TimePeriod.0000000073.01381X0069-S"><gml:beginPosition>1970-01-04T23:00:00Z</gml:beginPosition><gml:endPosition/></gml:TimePeriod></ef:linkingTime><ef:belongsTo xlink:href="http://ressource.brgm.fr/data/DispositifCollecte/0000000073" xlink:title="Réseau national de suivi quantitatif des eaux souterraines sous MO BRGM(RNESOUPMOBRGM)"/><ef:contains/></ef:NetworkFacility></ef:belongsTo><ef:belongsTo><ef:NetworkFacility gml:id="ef_networkfacility.fid-3a57c72a_1532cb9bf84_2cd2"><ef:linkingTime><gml:TimePeriod gml:id="TimePeriod.0200000002.01381X0069-S"><gml:beginPosition>1970-01-04T23:00:00Z</gml:beginPosition><gml:endPosition/></gml:TimePeriod></ef:linkingTime><ef:belongsTo xlink:href="http://ressource.brgm.fr/data/DispositifCollecte/0200000002" xlink:title="Méta Réseau de suivi piézométrique des eaux souterraines du bassin Rhin-Meuse (RBEST)(RBESOUPRM)"/><ef:contains/></ef:NetworkFacility></ef:belongsTo><ef:belongsTo><ef:NetworkFacility gml:id="ef_networkfacility.fid-3a57c72a_1532cb9bf84_2cd3"><ef:linkingTime><gml:TimePeriod gml:id="TimePeriod.RH-MEUS-TP.01381X0069-S"><gml:beginPosition>2000-05-30T10:36:47Z</gml:beginPosition><gml:endPosition/></gml:TimePeriod></ef:linkingTime><ef:belongsTo xlink:href="http://ressource.brgm.fr/data/DispositifCollecte/RH-MEUS-TP" xlink:title="RESEAU QUALITE DES EAUX SOUTERRAINES  EN RHIN MEUSE"/><ef:contains/></ef:NetworkFacility></ef:belongsTo><ef:belongsTo><ef:NetworkFacility gml:id="ef_networkfacility.fid-3a57c72a_1532cb9bf84_2cd4"><ef:linkingTime><gml:TimePeriod gml:id="TimePeriod.0000000029.01381X0069-S"><gml:beginPosition>1970-01-04T23:00:00Z</gml:beginPosition><gml:endPosition/></gml:TimePeriod></ef:linkingTime><ef:belongsTo xlink:href="http://ressource.brgm.fr/data/DispositifCollecte/0000000029" xlink:title="Réseau patrimonial national de suivi quantitatif des eaux souterraines(RNESP)"/><ef:contains/></ef:NetworkFacility></ef:belongsTo><ef:belongsTo><ef:NetworkFacility gml:id="ef_networkfacility.fid-3a57c72a_1532cb9bf84_2cd5"><ef:linkingTime><gml:TimePeriod gml:id="TimePeriod.0200000078.01381X0069-S"><gml:beginPosition>1970-01-04T23:00:00Z</gml:beginPosition><gml:endPosition/></gml:TimePeriod></ef:linkingTime><ef:belongsTo xlink:href="http://ressource.brgm.fr/data/DispositifCollecte/0200000078" xlink:title="Réseau de suivi piézométrique des eaux souterraines du BRGM Lorraine(RRESOUPBRGMLOR)"/><ef:contains/></ef:NetworkFacility></ef:belongsTo><ef:belongsTo><ef:NetworkFacility gml:id="ef_networkfacility.fid-3a57c72a_1532cb9bf84_2cd6"><ef:linkingTime><gml:TimePeriod gml:id="TimePeriod.0200000004.01381X0069-S"><gml:beginPosition>1970-01-04T23:00:00Z</gml:beginPosition><gml:endPosition/></gml:TimePeriod></ef:linkingTime><ef:belongsTo xlink:href="http://ressource.brgm.fr/data/DispositifCollecte/0200000004" xlink:title="Réseau de suivi piézométrique des eaux souterraines du bassin Rhin-Meuse (MO BRGM)(RBESOUPRMBRGM)"/><ef:contains/></ef:NetworkFacility></ef:belongsTo></ef:EnvironmentalMonitoringFacility></wfs:member></wfs:FeatureCollection>